mm_btc/__init__.py
mm_btc/blockstream.py
mm_btc/py.typed
mm_btc/tx.py
mm_btc/wallet.py
mm_btc/cli/__init__.py
mm_btc/cli/cli.py
mm_btc/cli/cmd/__init__.py
mm_btc/cli/cmd/address_cmd.py
mm_btc/cli/cmd/create_tx_cmd.py
mm_btc/cli/cmd/decode_tx_cmd.py
mm_btc/cli/cmd/mnemonic_cmd.py
mm_btc/cli/cmd/utxo_cmd.py
mm_btc-0.5.4.dist-info/METADATA
mm_btc-0.5.4.dist-info/WHEEL
mm_btc-0.5.4.dist-info/entry_points.txt
mm_btc-0.5.4.dist-info/RECORD
