Metadata-Version: 2.4
Name: mm-btc
Version: 0.5.4
Requires-Python: >=3.13
Requires-Dist: bitcoinlib~=0.7.5
Requires-Dist: bit~=0.8.0
Requires-Dist: hdwallet~=3.6.1
Requires-Dist: mm-web3~=0.5.2
Requires-Dist: mnemonic~=0.21
Requires-Dist: typer~=0.16.1
